deucalion/__init__.py
deucalion/observer.py
deucalion/provisioner.py
deucalion/requirements.txt
deucalion/strategies/__init__.py
deucalion/strategies/demo.py
deucalion/strategies/factory.py
deucalion/strategies/federated.py
deucalion/strategies/sidecar.py
deucalion/strategies/strategy.py
deucalion-0.0.1.dist-info/LICENSE
deucalion-0.0.1.dist-info/WHEEL
deucalion-0.0.1.dist-info/METADATA
deucalion-0.0.1.dist-info/RECORD
